willamette_client/__init__.py
willamette_client/client.py
willamette_client/api_v1/__init__.py
willamette_client/api_v1/models/__init__.py
willamette_client/api_v1/models/web_pages.py
willamette_client/api_v1/models/web_sites.py
willamette_client/api_v1/resources/__init__.py
willamette_client/api_v1/resources/web_pages.py
willamette_client/api_v1/resources/web_sites.py
quaerere_willamette_client-0.1.0a2.dist-info/LICENSE.txt
quaerere_willamette_client-0.1.0a2.dist-info/METADATA
quaerere_willamette_client-0.1.0a2.dist-info/WHEEL
quaerere_willamette_client-0.1.0a2.dist-info/entry_points.txt
quaerere_willamette_client-0.1.0a2.dist-info/top_level.txt
quaerere_willamette_client-0.1.0a2.dist-info/RECORD
